[
  {
    "date": "01",
    "title": "ថ្ងៃគ្មានការរើសអើង",
    "description": "គំនិតផ្តួចផ្តើមរបស់ UNAIDS ដើម្បីប្រយុទ្ធប្រឆាំងការរើសអើងគ្រប់ទម្រង់។ ការតស៊ូពេញមួយជីវិតរបស់បណ្ឌិត អាំបេដការ ប្រឆាំងការរើសអើងតាមវណ្ណៈ បញ្ជាក់ស្មារតីសមភាពនេះ។",
    "category": "event",
    "year": null,
    "isSymbolic": false
  },
  {
    "date": "01",
    "title": "ចលនាថ្ងៃទី១ ខែមីនា នៅកូរ៉េ",
    "description": "នៅថ្ងៃទី១ ខែមីនា ឆ្នាំ១៩១៩ អ្នកសកម្មកម្មកូរ៉េបានអានសេចក្តីប្រកាសឯករាជ្យជាសាធារណៈ ធ្វើឱ្យមានការបះបោរទូទាំងប្រទេសប្រឆាំងអាណានិគមជប៉ុន។ ប្រជាជនកូរ៉េប្រមាណពីរលាននាក់បានចូលរួមក្នុងបាតុកម្មជាង១៥០០។",
    "category": "event",
    "year": "1919",
    "isSymbolic": false
  },
  {
    "date": "01",
    "title": "ហង់រី បិគឺរល រកឃើញវិទ្យុសកម្ម",
    "description": "នៅថ្ងៃទី១ ខែមីនា ឆ្នាំ១៨៩៦ រូបវិទ្យាជនបារាំង ហង់រី បិគឺរល បានរកឃើញវិទ្យុសកម្មធម្មជាតិនៅពេលឃើញអំបិលអ៊ុយរ៉ានីញ៉ូមបានធ្វើឱ្យផ្ទាំងថតរូបក្នុងហិបងងឹតមានរូប។ ការរកឃើញនេះបានបើកផ្លូវទៅរូបវិទ្យានុយក្លេអ៊ែរ។",
    "category": "event",
    "year": "1896",
    "isSymbolic": false
  },
  {
    "date": "02",
    "title": "ធម៌៖ សីលប្រាំ",
    "description": "បញ្ចសីល — គោលការណ៍សីលធម៌ប្រាំសម្រាប់ពុទ្ធបរិស័ទគ្រហស្ថ៖ បដិសេធពីការសម្លាប់ ការលួច ការប្រព្រឹត្តខុសផ្លូវកាម ការនិយាយមិនពិត និងសារធាតុស្រវឹង។ គ្រឹះនៃជីវិតមានសីលធម៌។",
    "category": "event",
    "year": null,
    "isSymbolic": true
  },
  {
    "date": "02",
    "title": "សត្យាគ្រះចូលវត្តកាលារ៉ាម",
    "description": "នៅថ្ងៃទី២ ខែមីនា ឆ្នាំ១៩៣០ បណ្ឌិត អាំបេដការ បានចាប់ផ្តើមសត្យាគ្រះវត្តកាលារ៉ាមនៅណាស៊ីក ទាមទារសិទ្ធិរបស់ដាលីតចូលវត្តហិណ្ឌូ។ មនុស្សរាប់ពាន់នាក់បានដង្ហែរយ៉ាងសន្តិភាពទៅមាត់ទ្វារវត្ត។",
    "category": "event",
    "year": "1930",
    "isSymbolic": false
  },
  {
    "date": "02",
    "title": "សភាសហរដ្ឋអាមេរិកហាមពាណិជ្ជកម្មទាសករ",
    "description": "នៅថ្ងៃទី២ ខែមីនា ឆ្នាំ១៨០៧ ប្រធានាធិបតី ថូម៉ាស ជេហ្វឺសុន បានចុះហត្ថលេខាលើច្បាប់ហាមនាំចូលទាសករ ហាមពាណិជ្ជកម្មទាសករឆ្លងអាត្លង់ទិកទៅសហរដ្ឋអាមេរិកចាប់ពីថ្ងៃទី១ ខែមករា ឆ្នាំ១៨០៨។",
    "category": "event",
    "year": "1807",
    "isSymbolic": false
  },
  {
    "date": "03",
    "title": "ថ្ងៃសត្វព្រៃពិភពលោក",
    "description": "ថ្ងៃអង្គការសហប្រជាជាតិអបអរសត្វព្រៃនិងរុក្ខជាតិពិភពលោក។ មេត្តារបស់ព្រះពុទ្ធបានលាតសន្ធឹងដល់សត្វលោកទាំងអស់ — 'ទាំងអស់ភ័យញ័រពីអំពើហិង្សា ទាំងអស់ភ័យខ្លាចសេចក្តីស្លាប់។'",
    "category": "event",
    "year": null,
    "isSymbolic": false
  },
  {
    "date": "03",
    "title": "ការរំដោះកសិករទាសករនៅរុស្ស៊ី",
    "description": "នៅថ្ងៃទី៣ ខែមីនា ឆ្នាំ១៨៦១ ព្រះចៅអធិរាជ អាឡិចសាន់ឌ្រឺ ទី២ បានចុះហត្ថលេខាលើសេចក្តីប្រកាសរំដោះ តាំងពីកសិករទាសករជាង២៣លាននាក់នៅចក្រភពរុស្ស៊ីឱ្យមានសេរីភាព។",
    "category": "event",
    "year": "1861",
    "isSymbolic": false
  },
  {
    "date": "03",
    "title": "បាតុកម្មសិទ្ធិបោះឆ្នោតស្ត្រីនៅវ៉ាស៊ីនតោន",
    "description": "នៅថ្ងៃទី៣ ខែមីនា ឆ្នាំ១៩១៣ ស្ត្រីជាង៥០០០នាក់បានដង្ហែរនៅវ៉ាស៊ីនតោន ឌីស៊ី ទាមទារសិទ្ធិបោះឆ្នោត។ នេះបានជំរុញចលនាដែលនាំទៅវិសោធនកម្មទី១៩ ក្នុងឆ្នាំ១៩២០។",
    "category": "event",
    "year": "1913",
    "isSymbolic": false
  },
  {
    "date": "04",
    "title": "ថ្ងៃសុវត្ថិភាពជាតិ",
    "description": "ថ្ងៃសុវត្ថិភាពជាតិឥណ្ឌាជំរុញការយល់ដឹងអំពីវិធានសុវត្ថិភាពនៅកន្លែងធ្វើការនិងជីវិតប្រចាំថ្ងៃ។ ការការពារសិទ្ធិកម្មករគឺជាចំណុចស្នូលនៃកំណែទម្រង់ការងាររបស់បណ្ឌិត អាំបេដការ។",
    "category": "event",
    "year": null,
    "isSymbolic": false
  },
  {
    "date": "04",
    "title": "អាប្រាហាំ លីនខុល ស្បថជាប្រធានាធិបតី",
    "description": "នៅថ្ងៃទី៤ ខែមីនា ឆ្នាំ១៨៦១ អាប្រាហាំ លីនខុល បានស្បថជាប្រធានាធិបតីទី១៦ នៃសហរដ្ឋអាមេរិក។ រដ្ឋភាគខាងត្បូងប្រាំពីរបានបំបែកខ្លួនរួចហើយដោយសារបញ្ហាទាសករ។ រដ្ឋាភិបាលរបស់គាត់បានដឹកនាំសង្គ្រាមស៊ីវិល ហើយលុបបំបាត់ទាសករតាមវិសោធនកម្មទី១៣។",
    "category": "event",
    "year": "1861",
    "isSymbolic": false
  },
  {
    "date": "04",
    "title": "FDR ស្បថក្នុងវិបត្តិសេដ្ឋកិច្ចធំ",
    "description": "នៅថ្ងៃទី៤ ខែមីនា ឆ្នាំ១៩៣៣ ហ្វ្រែងគ្លីន រូសវែល បានស្បថដោយប្រកាសថា 'អ្វីដែលយើងត្រូវភ័យគឺភាពភ័យខ្លាចខ្លួនឯងតែប៉ុណ្ណោះ'។ គាត់បានចាប់ផ្តើម New Deal ផ្លាស់ប្តូររដ្ឋាភិបាលអាមេរិក និងជួយវណ្ណៈកម្មករ។",
    "category": "event",
    "year": "1933",
    "isSymbolic": false
  },
  {
    "date": "05",
    "title": "ធម៌៖ សមាធិ (ការផ្តោតអារម្មណ៍)",
    "description": "សមាធិគឺជាការផ្តោតអារម្មណ៍មួយចំណុចនៃចិត្ត។ តាមការអនុវត្តសមាធិជាប់លាប់ ចិត្តក្លាយជាស្ងប់ មានការផ្តោត និងអាចយល់ដឹងជ្រៅអំពីធម្មជាតិនៃការពិត។",
    "category": "event",
    "year": null,
    "isSymbolic": true
  },
  {
    "date": "05",
    "title": "ការសម្លាប់រង្គាលនៅបូស្តុន",
    "description": "នៅថ្ងៃទី៥ ខែមីនា ឆ្នាំ១៧៧០ ទាហានអង់គ្លេសបានបាញ់ចូលហ្វូងប្រជាជននៅបូស្តុន សម្លាប់មនុស្សប្រាំនាក់។ ក្នុងចំណោមនោះមាន គ្រីសប៉ុស អាតតាក់ ដែលចាត់ទុកជាអ្នកស្លាប់ដំបូងនៃបដិវត្តន៍អាមេរិក។",
    "category": "event",
    "year": "1770",
    "isSymbolic": false
  },
  {
    "date": "05",
    "title": "ការស្លាប់របស់យ៉ូសែប ស្តាលីន",
    "description": "នៅថ្ងៃទី៥ ខែមីនា ឆ្នាំ១៩៥៣ ផ្តាច់ការសូវៀត យ៉ូសែប ស្តាលីន បានស្លាប់នៅម៉ូស្គូ។ ការស្លាប់របស់គាត់បានបញ្ចប់ការគ្រប់គ្រងជិតបីទសវត្សរ៍ដែលសម្គាល់ដោយការបោសសម្អាតទ្រង់ទ្រាយធំនិងប្រព័ន្ធ Gulag។",
    "category": "event",
    "year": "1953",
    "isSymbolic": false
  },
  {
    "date": "06",
    "title": "ធម៌៖ កម្ម (សកម្មភាពនិងផល)",
    "description": "កម្មបង្រៀនថាសកម្មភាពមានចេតនាមានផល។ សកម្មភាពល្អនាំទៅរកសុខ អំពើអាក្រក់នាំទៅរកទុក្ខ។ យើងជាអ្នកស្នងមរតកនៃទង្វើផ្ទាល់ខ្លួន។",
    "category": "event",
    "year": null,
    "isSymbolic": true
  },
  {
    "date": "06",
    "title": "សេចក្តីសម្រេចឌ្រេត ស្កុត",
    "description": "នៅថ្ងៃទី៦ ខែមីនា ឆ្នាំ១៨៥៧ តុលាការកំពូលអាមេរិកបានសម្រេចថាជនអាហ្វ្រិកអាមេរិកមិនមែនជាពលរដ្ឋ។ សេចក្តីសម្រេចនេះបានធ្វើឱ្យវិបត្តិទាសករកាន់តែធ្ងន់ធ្ងរ និងពន្លឿនសង្គ្រាមស៊ីវិល។",
    "category": "event",
    "year": "1857",
    "isSymbolic": false
  },
  {
    "date": "06",
    "title": "អាស្ពីរីនចុះបញ្ជីជាយីហោពាណិជ្ជកម្ម",
    "description": "នៅថ្ងៃទី៦ ខែមីនា ឆ្នាំ១៨៩៩ ក្រុមហ៊ុនឱសថអាល្លឺម៉ង់ Bayer បានចុះបញ្ជីអាស្ពីរីនជាយីហោពាណិជ្ជកម្ម។ វាបានក្លាយជាថ្នាំប្រើយ៉ាងទូលំទូលាយបំផុតមួយលើពិភពលោក។",
    "category": "event",
    "year": "1899",
    "isSymbolic": false
  },
  {
    "date": "07",
    "title": "ធម៌៖ សម្មា វាយាមៈ (ការខិតខំត្រឹមត្រូវ)",
    "description": "ការខិតខំត្រឹមត្រូវមានផ្នែកបួន៖ ការពារមិនឱ្យអកុសលកើតឡើង បង្ក្រាបអកុសលដែលកើតឡើយ ចម្រើនសភាពល្អ និងថែរក្សាសភាពល្អដែលមានរួចហើយ។",
    "category": "event",
    "year": null,
    "isSymbolic": true
  },
  {
    "date": "07",
    "title": "ថ្ងៃអាទិត្យបង់ឈាមនៅសេលម៉ា អាឡាបាម៉ា",
    "description": "នៅថ្ងៃទី៧ ខែមីនា ឆ្នាំ១៩៦៥ បាតុករសិទ្ធិពលរដ្ឋប្រមាណ៦០០នាក់ដែលព្យាយាមដើរពីសេលម៉ាទៅម៉ុងហ្គោមេរី ត្រូវបានប៉ូលីសវាយប្រហារយ៉ាងព្រៃផ្សៃនៅស្ពានអេដម៉ុន ភើទឹស។ នេះបានជំរុញការគាំទ្រច្បាប់សិទ្ធិបោះឆ្នោតឆ្នាំ១៩៦៥។",
    "category": "event",
    "year": "1965",
    "isSymbolic": false
  },
  {
    "date": "07",
    "title": "អាឡិចសាន់ឌឺ ហ្គ្រាហាម បែល ទទួលប៉ាតង់ទូរស័ព្ទ",
    "description": "នៅថ្ងៃទី៧ ខែមីនា ឆ្នាំ១៨៧៦ អាឡិចសាន់ឌឺ ហ្គ្រាហាម បែល បានទទួលប៉ាតង់អាមេរិកសម្រាប់ទូរស័ព្ទ។ ការរកឃើញរបស់គាត់បានបដិវត្តន៍ការទំនាក់ទំនងរបស់មនុស្ស។",
    "category": "event",
    "year": "1876",
    "isSymbolic": false
  },
  {
    "date": "08",
    "title": "ថ្ងៃស្ត្រីអន្តរជាតិ",
    "description": "ថ្ងៃពិភពលោកអបអរសមិទ្ធិផលស្ត្រី។ សាវិត្រីបាយ ហ្វូឡេ បណ្ឌិតា រាមាបាយ និងអ្នកដទៃទៀតបានបំបែកឧបសគ្គដើម្បីនាំការអប់រំនិងយុត្តិធម៌មកស្ត្រីឥណ្ឌា។",
    "category": "festival",
    "year": null,
    "isSymbolic": false
  },
  {
    "date": "08",
    "title": "បដិវត្តន៍ខែកុម្ភៈនៅរុស្ស៊ីចាប់ផ្តើម",
    "description": "នៅថ្ងៃទី៨ ខែមីនា ឆ្នាំ១៩១៧ កម្មការិនីវាយនភ័ណ្ឌនៅពេត្រូគ្រាដបានធ្វើកូដកម្មទាមទារនំប៉័ងនិងបញ្ចប់សង្គ្រាមលោកលើកទី១។ នេះបាននាំឱ្យស្តេចនីកូឡា ទី២ លះបង់រាជបល្ល័ង្ក។",
    "category": "event",
    "year": "1917",
    "isSymbolic": false
  },
  {
    "date": "08",
    "title": "កងទ័ពប្រយុទ្ធអាមេរិកដំបូងមកដល់វៀតណាម",
    "description": "នៅថ្ងៃទី៨ ខែមីនា ឆ្នាំ១៩៦៥ ទាហានម៉ារីនអាមេរិក៣៥០០នាក់បានចុះចតនៅដាណាង វៀតណាមខាងត្បូង ក្លាយជាកងទ័ពប្រយុទ្ធអាមេរិកដំបូងក្នុងសង្គ្រាមវៀតណាម។",
    "category": "event",
    "year": "1965",
    "isSymbolic": false
  },
  {
    "date": "09",
    "title": "ធម៌៖ ទុក្ខ",
    "description": "សច្ចទី១៖ ជីវិតមានទុក្ខ — កំណើត ចាស់ ឈឺ ស្លាប់ និងការបែកបាក់ពីអ្នកស្រឡាញ់។ ការទទួលស្គាល់ទុក្ខគឺជាចំណុចផ្តើមនៃផ្លូវឆ្ពោះទៅរកការរំដោះ។",
    "category": "event",
    "year": null,
    "isSymbolic": true
  },
  {
    "date": "09",
    "title": "សំណុំរឿងអាមីស្តាដត្រូវតុលាការកំពូលសម្រេច",
    "description": "នៅថ្ងៃទី៩ ខែមីនា ឆ្នាំ១៨៤១ តុលាការកំពូលអាមេរិកបានសម្រេចថាជនអាហ្វ្រិកដែលបានកាន់កាប់នាវា La Amistad គឺជាបុគ្គលសេរី។ នេះជាជ័យជម្នះសំខាន់នៃចលនាប្រឆាំងទាសករ។",
    "category": "event",
    "year": "1841",
    "isSymbolic": false
  },
  {
    "date": "09",
    "title": "សមរភូមិនាវាដែក៖ ម៉ូនីទ័រ vs វើជីនៀ",
    "description": "នៅថ្ងៃទី៩ ខែមីនា ឆ្នាំ១៨៦២ USS Monitor និង CSS Virginia បានប្រយុទ្ធនៅ Hampton Roads — សមរភូមិនាវាដែកដំបូងក្នុងប្រវត្តិសាស្ត្រ។ នេះបានធ្វើឱ្យនាវាឈើហួសសម័យភ្លាមៗ។",
    "category": "event",
    "year": "1862",
    "isSymbolic": false
  },
  {
    "date": "10",
    "title": "សាវិត្រីបាយ ហ្វូឡេ បុណ្យាទិថិ",
    "description": "ការរំលឹកសាវិត្រីបាយ ហ្វូឡេ ដែលស្លាប់ដោយជំងឺប៉េស្តក្នុងឆ្នាំ១៨៩៧ ពេលថែទាំអ្នកជំងឺ។ ការងារឈានមុខរបស់នាងសម្រាប់ការអប់រំស្ត្រីនៅតែជាការបំផុសគំនិត។",
    "category": "event",
    "year": "1897",
    "isSymbolic": false
  },
  {
    "date": "10",
    "title": "បែលធ្វើការហៅទូរស័ព្ទដំបូង",
    "description": "នៅថ្ងៃទី១០ ខែមីនា ឆ្នាំ១៨៧៦ អាឡិចសាន់ឌឺ ហ្គ្រាហាម បែល បាននិយាយថា 'លោកវ៉ាតសុន មកទីនេះ' ហើយធ្វើការហៅទូរស័ព្ទជោគជ័យដំបូង។ នេះជាកំណើតនៃទូរគមនាគមន៍សំឡេង។",
    "category": "event",
    "year": "1876",
    "isSymbolic": false
  },
  {
    "date": "10",
    "title": "ការបះបោរទីបេប្រឆាំងអំណាចចិន",
    "description": "នៅថ្ងៃទី១០ ខែមីនា ឆ្នាំ១៩៥៩ ជនជាតិទីបេរាប់ពាន់នាក់បានឡោមព័ទ្ធវាំងណ័រប៊ូលីងកានៅឡាសា។ កងទ័ពចិនបានសម្លាប់មនុស្សរាប់ពាន់នាក់ ហើយបង្ខំឱ្យដាឡៃឡាម៉ារត់គេចទៅឥណ្ឌា។",
    "category": "event",
    "year": "1959",
    "isSymbolic": false
  },
  {
    "date": "11",
    "title": "ធម៌៖ ធម្មបទ",
    "description": "'ចិត្តជាអ្នកនាំមុខនៃសកម្មភាពទាំងអស់។ សកម្មភាពទាំងអស់ត្រូវបាននាំដោយចិត្ត បង្កើតដោយចិត្ត។' — ធម្មបទ គាថា១។ ការណែនាំដ៏អស់កល្បសម្រាប់ជីវិតសីលធម៌និងវិន័យផ្លូវចិត្ត។",
    "category": "event",
    "year": null,
    "isSymbolic": true
  },
  {
    "date": "11",
    "title": "លីទុយអានីប្រកាសឯករាជ្យពីសហភាពសូវៀត",
    "description": "នៅថ្ងៃទី១១ ខែមីនា ឆ្នាំ១៩៩០ លីទុយអានីបានក្លាយជាសាធារណរដ្ឋសូវៀតដំបូងដែលប្រកាសឯករាជ្យ។ នេះបានជំរុញចលនាឯករាជ្យនៅបាល់ទិក និងរួមចំណែកដល់ការបែកបាក់សហភាពសូវៀតក្នុងឆ្នាំ១៩៩១។",
    "category": "event",
    "year": "1990",
    "isSymbolic": false
  },
  {
    "date": "11",
    "title": "គ្រោះមហន្តរាយនុយក្លេអ៊ែរហ្វុគុស៊ីម៉ា",
    "description": "នៅថ្ងៃទី១១ ខែមីនា ឆ្នាំ២០១១ រញ្ជួយដី៩.០និងរលកយក្សស៊ូណាមិបានវាយប្រហារភាគឦសានជប៉ុន ធ្វើឱ្យមានការរលាយនៅរោងចក្រថាមពលនុយក្លេអ៊ែរហ្វុគុស៊ីម៉ា ដៃអ៊ីឈិ។ វាជាគ្រោះមហន្តរាយនុយក្លេអ៊ែរធ្ងន់បំផុតបន្ទាប់ពីឆឺណូប៊ីល។",
    "category": "event",
    "year": "2011",
    "isSymbolic": false
  },
  {
    "date": "12",
    "title": "ធម៌៖ សូត្តរបិដក",
    "description": "សូត្តរបិដកមានសេចក្តីអធិប្បាយរបស់ព្រះពុទ្ធដែលបានសំដែងអស់រយៈពេល៤៥ឆ្នាំ។ វារក្សាសន្ទនា ឧទាហរណ៍ និងការបង្រៀនដែលណែនាំមនុស្សរាប់លាននាក់លើផ្លូវភ្ញាក់រលឹក។",
    "category": "event",
    "year": null,
    "isSymbolic": true
  },
  {
    "date": "12",
    "title": "គន្ធីចាប់ផ្តើមដង្ហែរអំបិល",
    "description": "នៅថ្ងៃទី១២ ខែមីនា ឆ្នាំ១៩៣០ មហាត្មៈ គន្ធី បានចេញពីសាប័រម៉ាទីអាស្រមនៅអាហ្ម៉ាដាបាទជាមួយសិស្ស៧៨នាក់ដើរចម្ងាយ២៤០ម៉ាយល៍ទៅដាន់ឌី។ ដង្ហែរអំបិលបានក្លាយជាទង្វើតស៊ូអហិំសាដ៏ល្បីល្បាញបំផុតមួយក្នុងប្រវត្តិសាស្ត្រ។",
    "category": "event",
    "year": "1930",
    "isSymbolic": false
  },
  {
    "date": "12",
    "title": "គោលលទ្ធិត្រូមែនត្រូវបានប្រកាស",
    "description": "នៅថ្ងៃទី១២ ខែមីនា ឆ្នាំ១៩៤៧ ប្រធានាធិបតី ហារី ត្រូមែន បានប្រកាសគោលលទ្ធិត្រូមែន សន្យាជួយប្រទេសដែលតស៊ូប្រឆាំងការពង្រីកកុម្មុយនិស្ត។ នេះជាដើមកំណើតយុទ្ធសាស្ត្រសង្គ្រាមត្រជាក់។",
    "category": "event",
    "year": "1947",
    "isSymbolic": false
  },
  {
    "date": "13",
    "title": "ធម៌៖ សច្ចភាពដ៏ថ្លៃថ្នូរ",
    "description": "ក្នុងការអនុវត្តវិបស្សនា សច្ចភាពដ៏ថ្លៃថ្នូរត្រូវបានរក្សា — បញ្ឈប់ការនិយាយ សញ្ញាដៃ និងការសរសេរ។ សច្ចភាពអនុញ្ញាតឱ្យចិត្តងាកចូលក្នុង ហើយមើលធម្មជាតិខ្លួនឯង។",
    "category": "event",
    "year": null,
    "isSymbolic": true
  },
  {
    "date": "13",
    "title": "វីល្លៀម ហឺសសែល រកឃើញអ៊ុយរ៉ានុស",
    "description": "នៅថ្ងៃទី១៣ ខែមីនា ឆ្នាំ១៧៨១ វីល្លៀម ហឺសសែល បានសង្កេតវត្ថុដែលបន្ទាប់មកបញ្ជាក់ថាជាភពអ៊ុយរ៉ានុស។ នេះជាភពដំបូងដែលរកឃើញដោយកែវយឺត។",
    "category": "event",
    "year": "1781",
    "isSymbolic": false
  },
  {
    "date": "13",
    "title": "កូដកម្មទូទៅរបស់កម្មករកម្ទេចការបះបោរ Kapp",
    "description": "នៅថ្ងៃទី១៣ ខែមីនា ឆ្នាំ១៩២០ និយមជាតិខាងស្តាំបានព្យាយាមកំទេចសាធារណរដ្ឋវ៉ៃម៉ា។ កម្មករអាល្លឺម៉ង់រាប់លាននាក់បានធ្វើកូដកម្មទូទៅ។ ក្នុងរយៈពេលបួនថ្ងៃការបះបោរបានបរាជ័យ។",
    "category": "event",
    "year": "1920",
    "isSymbolic": false
  },
  {
    "date": "14",
    "title": "ហូលី — ពិធីបុណ្យពណ៌",
    "description": "ហូលីអបអរជ័យជម្នះនៃអំពើល្អលើអំពើអាក្រក់និងការមកដល់នៃនិទាឃរដូវ។ ពិធីបុណ្យពណ៌ តន្ត្រី និងសហគមន៍ដែលហួសពីឧបសគ្គវណ្ណៈនិងវណ្ណៈសង្គម។",
    "category": "festival",
    "year": null,
    "isSymbolic": true
  },
  {
    "date": "14",
    "title": "អាល់បឺត អែងស្តែងកើត",
    "description": "នៅថ្ងៃទី១៤ ខែមីនា ឆ្នាំ១៨៧៩ អាល់បឺត អែងស្តែង បានកើតនៅអ៊ុលម៍ ប្រទេសអាល្លឺម៉ង់។ គាត់បានអភិវឌ្ឍទ្រឹស្តីភាពទាក់ទង ហើយផ្លាស់ប្តូរការយល់ដឹងអំពីលំហ ពេលវេលា ថាមពល និងទំនាញ។ ទទួលរង្វាន់ណូបែលរូបវិទ្យាឆ្នាំ១៩២១។",
    "category": "event",
    "year": "1879",
    "isSymbolic": false
  },
  {
    "date": "14",
    "title": "អេលី វីតនីទទួលប៉ាតង់ម៉ាស៊ីនសំណុំកប្បាស",
    "description": "នៅថ្ងៃទី១៤ ខែមីនា ឆ្នាំ១៧៩៤ អេលី វីតនី បានទទួលប៉ាតង់ម៉ាស៊ីនបំបែកគ្រាប់កប្បាស។ វាបានបដិវត្តន៍ផលិតកម្មកប្បាស ប៉ុន្តែបានបង្កើនតម្រូវការពលកម្មទាសករយ៉ាងខ្លាំងនៅភាគខាងត្បូងអាមេរិក។",
    "category": "event",
    "year": "1794",
    "isSymbolic": false
  },
  {
    "date": "15",
    "title": "កាន្ស៊ី រ៉ាម ជ័យន្តិ",
    "description": "ថ្ងៃកំណើតរបស់កាន្ស៊ី រ៉ាម ស្ថាបនិកគណបក្សបាហុជនសមាជ។ គាត់បានលះបង់ជីវិតសម្រាប់ការផ្តល់អំណាចនយោបាយដល់ដាលីត អាទិវាស និងសហគមន៍ដែលត្រូវបានគេបំភ្លេច។",
    "category": "event",
    "year": "1934",
    "isSymbolic": false
  },
  {
    "date": "15",
    "title": "ស្តេចនីកូឡា ទី២ លះបង់រាជបល្ល័ង្ក",
    "description": "នៅថ្ងៃទី១៥ ខែមីនា ឆ្នាំ១៩១៧ ស្តេចនីកូឡា ទី២ បានលះបង់រាជបល្ល័ង្ក បញ្ចប់ការគ្រប់គ្រងរាជវង្សរ៉ូម៉ាណូវជាង៣០០ឆ្នាំ។ នេះបានបើកផ្លូវឱ្យរដ្ឋាភិបាលបណ្តោះអាសន្ន និងទីបំផុតបូលសេវិក។",
    "category": "event",
    "year": "1917",
    "isSymbolic": false
  },
  {
    "date": "15",
    "title": "ប្រធានាធិបតីយ៉នសុនថ្លែងអំពីសិទ្ធិបោះឆ្នោត",
    "description": "នៅថ្ងៃទី១៥ ខែមីនា ឆ្នាំ១៩៦៥ ប្រធានាធិបតី លីនដុន យ៉នសុន បានថ្លែងនៅសភាបន្ទាប់ពីថ្ងៃអាទិត្យបង់ឈាមនៅសេលម៉ា ហើយទាមទារច្បាប់សិទ្ធិបោះឆ្នោត។ គាត់បាននិយាយថា 'We shall overcome'។",
    "category": "event",
    "year": "1965",
    "isSymbolic": false
  },
  {
    "date": "16",
    "title": "ថ្ងៃចាក់វ៉ាក់សាំងជាតិ",
    "description": "ការរំលឹកកម្មវិធីចាក់វ៉ាក់សាំងប៉ូលីយ៉ូរបស់ឥណ្ឌា។ សុខភាពសាធារណៈជាទំនួលខុសត្រូវរួម — ព្រះពុទ្ធបានសង្កត់ធ្ងន់ការថែរក្សាអ្នកឈឺជាអំពើបុណ្យ។",
    "category": "event",
    "year": null,
    "isSymbolic": false
  },
  {
    "date": "16",
    "title": "ហ្គោដដាតបាញ់រ៉ូកែតប្រេងរាវដំបូង",
    "description": "នៅថ្ងៃទី១៦ ខែមីនា ឆ្នាំ១៩២៦ រ៉ូបឺត ហ្គោដដាត បានបាញ់រ៉ូកែតប្រេងរាវដំបូងលើពិភពលោកដោយជោគជ័យនៅម៉ាស្សាឈូសិត។ នេះជាគ្រឹះនៃរ៉ូកែតសម័យទំនើប។",
    "category": "event",
    "year": "1926",
    "isSymbolic": false
  },
  {
    "date": "16",
    "title": "ការសម្លាប់រង្គាលម៉ៃឡាយនៅវៀតណាម",
    "description": "នៅថ្ងៃទី១៦ ខែមីនា ឆ្នាំ១៩៦៨ ទាហានអាមេរិកបានសម្លាប់ជនស៊ីវិលគ្មានអាវុធពី៣៤៧ដល់៥០៤នាក់នៅភូមិម៉ៃឡាយ។ នេះបានបង្កកំហឹងទូទាំងពិភពលោក ហើយធ្វើឱ្យចលនាប្រឆាំងសង្គ្រាមកាន់តែខ្លាំង។",
    "category": "event",
    "year": "1968",
    "isSymbolic": false
  },
  {
    "date": "17",
    "title": "ធម៌៖ វិន័យបិដក",
    "description": "វិន័យបិដកមានវិន័យសង្ឃដែលព្រះពុទ្ធបានតាំង។ វាគ្រប់គ្រងជីវិតសហគមន៍នៃសង្ឃ ធានាភាពសុខដុមនិងកិរិយាសីលធម៌។",
    "category": "event",
    "year": null,
    "isSymbolic": true
  },
  {
    "date": "17",
    "title": "កងទ័ពអង់គ្លេសដកខ្លួនពីបូស្តុន",
    "description": "នៅថ្ងៃទី១៧ ខែមីនា ឆ្នាំ១៧៧៦ កងទ័ពអង់គ្លេសបានដកខ្លួនពីបូស្តុន។ នេះជាជ័យជម្នះអាមេរិកសំខាន់ដំបូងនៃសង្គ្រាមបដិវត្តន៍។",
    "category": "event",
    "year": "1776",
    "isSymbolic": false
  },
  {
    "date": "17",
    "title": "ហ្គោលដា ម៉ៀរក្លាយជានាយករដ្ឋមន្ត្រីអ៊ីស្រាអែល",
    "description": "នៅថ្ងៃទី១៧ ខែមីនា ឆ្នាំ១៩៦៩ ហ្គោលដា ម៉ៀរ បានក្លាយជានាយករដ្ឋមន្ត្រីអ៊ីស្រាអែល — ស្ត្រីទីបីក្នុងពិភពសម័យទំនើបដែលដឹកនាំប្រទេស។ នាងបានដឹកនាំអ៊ីស្រាអែលតាមរយៈសង្គ្រាមយ៉មគីពពឺឆ្នាំ១៩៧៣។",
    "category": "event",
    "year": "1969",
    "isSymbolic": false
  },
  {
    "date": "18",
    "title": "ធម៌៖ សម្មា សតិ (ការរំលឹកត្រឹមត្រូវ)",
    "description": "ការរំលឹកត្រឹមត្រូវជាអង្គទីប្រាំពីរនៃមគ្គអដ្ឋង្គិក។ សតិបដ្ឋានសូត្តបង្រៀនមូលដ្ឋានបួន៖ កាយ វេទនា ចិត្ត និងធម្មៈ។",
    "category": "event",
    "year": null,
    "isSymbolic": true
  },
  {
    "date": "18",
    "title": "កុម្មុយនីប៉ារីសត្រូវបានបង្កើត",
    "description": "នៅថ្ងៃទី១៨ ខែមីនា ឆ្នាំ១៨៧១ ប្រជាជនប៉ារីសបានបះបោរបង្កើតកុម្មុយនីប៉ារីស។ វាបានគ្រប់គ្រងរយៈពេល៧២ថ្ងៃ ហើយក្លាយជានិមិត្តរូបនៃប្រជាធិបតេយ្យកម្មករ។",
    "category": "event",
    "year": "1871",
    "isSymbolic": false
  },
  {
    "date": "18",
    "title": "ការដើរអវកាសដំបូងរបស់អាឡិចស៊ី លេអូណូវ",
    "description": "នៅថ្ងៃទី១៨ ខែមីនា ឆ្នាំ១៩៦៥ លោកយោធាអវកាសសូវៀត អាឡិចស៊ី លេអូណូវ បានដើរនៅអវកាសប្រហែល១២នាទី ធ្វើឱ្យក្លាយជាការដើរអវកាសមនុស្សដំបូង។",
    "category": "event",
    "year": "1965",
    "isSymbolic": false
  },
  {
    "date": "19",
    "title": "ធម៌៖ និព្វាន (ការរំដោះ)",
    "description": "និព្វានជាគោលដៅចុងក្រោយនៃការអនុវត្តពុទ្ធសាសនា — ការរលត់ទាំងស្រុងនៃតណ្ហា ទោសៈ និងមោហៈ។ វាជាសភាពហួសពីទុក្ខនិងការកើតឡើងវិញ។",
    "category": "event",
    "year": null,
    "isSymbolic": true
  },
  {
    "date": "19",
    "title": "បងប្អូនលូមីយ៉ែថតភាពយន្តចលនាដំបូង",
    "description": "នៅថ្ងៃទី១៩ ខែមីនា ឆ្នាំ១៨៩៥ បងប្អូនលូមីយ៉ែបានថត 'កម្មករចេញពីរោងចក្រលូមីយ៉ែ' នៅលីយ៉ុង — ភាពយន្តចលនាពិតដំបូងក្នុងប្រវត្តិសាស្ត្រ។ នេះបានបើកកំណើតឧស្សាហកម្មភាពយន្តពិភពលោក។",
    "category": "event",
    "year": "1895",
    "isSymbolic": false
  },
  {
    "date": "19",
    "title": "ការឈប់បាញ់នៃសង្គ្រាមអាល់ហ្សេរីចាប់ផ្តើមមានប្រសិទ្ធភាព",
    "description": "នៅថ្ងៃទី១៩ ខែមីនា ឆ្នាំ១៩៦២ ការឈប់បាញ់ពីកិច្ចព្រមព្រៀងអេវីអង់ចាប់ផ្តើមមានប្រសិទ្ធភាព បញ្ចប់សង្គ្រាមអាល់ហ្សេរីប្រាំបីឆ្នាំ។ ឯករាជ្យត្រូវបានប្រកាសនៅថ្ងៃទី៥ ខែកក្កដា ឆ្នាំ១៩៦២។",
    "category": "event",
    "year": "1962",
    "isSymbolic": false
  },
  {
    "date": "20",
    "title": "ថ្ងៃចាបពិភពលោក",
    "description": "ថ្ងៃលើកកម្ពស់ការយល់ដឹងអំពីការថយចុះចំនួនចាបផ្ទះ។ មេត្តារបស់ព្រះពុទ្ធបានលាតសន្ធឹងដល់បក្សី សត្វ និងរាល់ទម្រង់ជីវិត។",
    "category": "event",
    "year": null,
    "isSymbolic": false
  },
  {
    "date": "20",
    "title": "សត្យាគ្រះមហាឌ៍ (ឆាវដារ តាលេ)",
    "description": "នៅថ្ងៃទី២០ ខែមីនា ឆ្នាំ១៩២៧ បណ្ឌិត អាំបេដការ បានដឹកនាំដាលីតរាប់ពាន់នាក់ឱ្យផឹកទឹកពីឆាវដារ តាលេ (អាងទឹកសាធារណៈ) នៅមហាឌ៍ មហារាស្ត្រ — អះអាងសិទ្ធិជាមូលដ្ឋានរបស់អ្នកមិនអាចប៉ះក្នុងការទទួលបានទឹកសាធារណៈ។ នេះជាការតស៊ូសិទ្ធិពលរដ្ឋសំខាន់ដំបូងដែលគាត់ដឹកនាំ។",
    "category": "event",
    "year": "1927",
    "isSymbolic": false
  },
  {
    "date": "20",
    "title": "សៀវភៅ Uncle Tom's Cabin ត្រូវបានបោះពុម្ព",
    "description": "នៅថ្ងៃទី២០ ខែមីនា ឆ្នាំ១៨៥២ ប្រលោមលោក Uncle Tom's Cabin របស់ហារីយ៉ែត ប៊ីឆឺ ស្តូវ ត្រូវបានបោះពុម្ពជាសៀវភៅ។ វាបានពណ៌នាអំពីភាពឃោឃៅនៃទាសករ ហើយផ្លាស់ប្តូរគំនិតសាធារណៈនៅភាគខាងជើង។",
    "category": "event",
    "year": "1852",
    "isSymbolic": false
  },
  {
    "date": "21",
    "title": "ថ្ងៃព្រៃឈើពិភពលោក",
    "description": "ថ្ងៃព្រៃឈើអន្តរជាតិ។ ព្រះពុទ្ធបានត្រាស់ដឹងក្រោមដើមពោធិ៍ក្នុងព្រៃ។ ព្រៃឈើជាចំណុចស្នូលនៃជីវិតសង្ឃនិងការអនុវត្តសមាធិ។",
    "category": "event",
    "year": null,
    "isSymbolic": false
  },
  {
    "date": "21",
    "title": "ការសម្លាប់រង្គាលឆារបវីលនៅអាហ្វ្រិកខាងត្បូង",
    "description": "នៅថ្ងៃទី២១ ខែមីនា ឆ្នាំ១៩៦០ ប៉ូលីសអាហ្វ្រិកខាងត្បូងបានបាញ់បាតុករស្បែកខ្មៅគ្មានអាវុធនៅឆារបវីលដែលប្រឆាំងច្បាប់លិខិតឆ្លងដែនអបភាងី។ យ៉ាងហោចណាស់៦៩នាក់ត្រូវបានសម្លាប់។ នេះជាចំណុចសំខាន់នៃការតស៊ូប្រឆាំងអបភាងី។",
    "category": "event",
    "year": "1960",
    "isSymbolic": false
  },
  {
    "date": "21",
    "title": "ដង្ហែរពីសេលម៉ាទៅម៉ុងហ្គោមេរីចាប់ផ្តើម",
    "description": "នៅថ្ងៃទី២១ ខែមីនា ឆ្នាំ១៩៦៥ បាតុករសិទ្ធិពលរដ្ឋប្រមាណ៣២០០នាក់ដែលដឹកនាំដោយបណ្ឌិត ម៉ាទីន លូធើរ ឃីង បានចាប់ផ្តើមដង្ហែរចម្ងាយ៥៤ម៉ាយល៍ពីសេលម៉ាទៅម៉ុងហ្គោមេរី។ នេះបាននាំទៅច្បាប់សិទ្ធិបោះឆ្នោតឆ្នាំ១៩៦៥។",
    "category": "event",
    "year": "1965",
    "isSymbolic": false
  },
  {
    "date": "22",
    "title": "ថ្ងៃទឹកពិភពលោក",
    "description": "ថ្ងៃអង្គការសហប្រជាជាតិសង្កត់ធ្ងន់សារៈសំខាន់នៃទឹកស្អាត។ ការទទួលបានទឹកជាសិទ្ធិជាមូលដ្ឋាន — បណ្ឌិត អាំបេដការ បានតស៊ូសម្រាប់សិទ្ធិដាលីតក្នុងការទទួលបានប្រភពទឹកសាធារណៈ។",
    "category": "event",
    "year": null,
    "isSymbolic": false
  },
  {
    "date": "22",
    "title": "សភាអង់គ្លេសអនុម័តច្បាប់ត្រា",
    "description": "នៅថ្ងៃទី២២ ខែមីនា ឆ្នាំ១៧៦៥ សភាអង់គ្លេសបានអនុម័តច្បាប់ត្រា ដាក់ពន្ធផ្ទាល់លើអាណានិគមអាមេរិក។ ក្រោមពាក្យស្លោក 'គ្មានពន្ធដោយគ្មានតំណាង' នេះបានរៀបចំឆាកសម្រាប់បដិវត្តន៍អាមេរិក។",
    "category": "event",
    "year": "1765",
    "isSymbolic": false
  },
  {
    "date": "22",
    "title": "សភាអាមេរិកអនុម័តវិសោធនកម្មសិទ្ធិស្មើ",
    "description": "នៅថ្ងៃទី២២ ខែមីនា ឆ្នាំ១៩៧២ ព្រឹទ្ធសភាអាមេរិកបានអនុម័តវិសោធនកម្មសិទ្ធិស្មើ — សិទ្ធិតាមច្បាប់មិនត្រូវបដិសេធដោយសារភេទ។ នេះបានជំរុញចលនាសិទ្ធិស្ត្រី។",
    "category": "event",
    "year": "1972",
    "isSymbolic": false
  },
  {
    "date": "23",
    "title": "ភាគាត់ ស៊ីង រ៉ាជ្គូរុ និងសុខទេវ បូជាជីវិត",
    "description": "នៅថ្ងៃនេះក្នុងឆ្នាំ១៩៣១ ភាគាត់ ស៊ីង រ៉ាជ្គូរុ និងសុខទេវ ត្រូវបានចងព្យួររន្ធដោយសារតួនាទីក្នុងការតស៊ូឯករាជ្យ។ ការលះបង់វ័យក្មេងរបស់ពួកគេបានឆេះស្មារតីបដិវត្តន៍ទូទាំងឥណ្ឌា។",
    "category": "event",
    "year": "1931",
    "isSymbolic": false
  },
  {
    "date": "23",
    "title": "សុន្ទរកថា 'សេរីភាព ឬសេចក្តីស្លាប់' របស់ប៉ាត្រិក ហេនរី",
    "description": "នៅថ្ងៃទី២៣ ខែមីនា ឆ្នាំ១៧៧៥ ប៉ាត្រិក ហេនរី បានថ្លែងនៅរីឆម៉ុនថា 'ឱ្យខ្ញុំនូវសេរីភាព ឬឱ្យខ្ញុំនូវសេចក្តីស្លាប់!' នេះបានក្លាយជាពាក្យស្លោកដ៏ល្បីបំផុតមួយនៃបដិវត្តន៍អាមេរិក។",
    "category": "event",
    "year": "1775",
    "isSymbolic": false
  },
  {
    "date": "23",
    "title": "ស្ថានីយអវកាសមីរត្រូវបាននាំចេញពីគន្លង",
    "description": "នៅថ្ងៃទី២៣ ខែមីនា ឆ្នាំ២០០១ ស្ថានីយអវកាសរុស្ស៊ីមីរត្រូវបាននាំឱ្យធ្លាក់ចូលមហាសមុទ្រប៉ាស៊ីហ្វិកខាងត្បូងដោយចេតនាបន្ទាប់ពី១៥ឆ្នាំ។ ការស្រាវជ្រាវរយៈពេលវែងរបស់មីរសំខាន់សម្រាប់ស្ថានីយអវកាសអន្តរជាតិ។",
    "category": "event",
    "year": "2001",
    "isSymbolic": false
  },
  {
    "date": "24",
    "title": "ថ្ងៃជំងឺរបេងពិភពលោក",
    "description": "ថ្ងៃលើកកម្ពស់ការយល់ដឹងអំពីជំងឺរបេង។ សមភាពសុខភាពជាកង្វល់របស់បណ្ឌិត អាំបេដការ — គាត់បានទាមទារហេដ្ឋារចនាសម្ព័ន្ធសុខភាពសាធារណៈដែលអាចចូលដំណើរការបានសម្រាប់សហគមន៍ទាំងអស់។",
    "category": "event",
    "year": null,
    "isSymbolic": false
  },
  {
    "date": "24",
    "title": "កូកប្រកាសការរកឃើញបាក់តេរីរបេង",
    "description": "នៅថ្ងៃទី២៤ ខែមីនា ឆ្នាំ១៨៨២ គ្រូពេទ្យអាល្លឺម៉ង់ រ៉ូបឺត កូក បានប្រកាសនៅបែរលីនអំពីការរកឃើញបាក់តេរីបង្កជំងឺរបេង។ នេះបានបដិវត្តន៍ការយល់ដឹងអំពីជំងឺឆ្លង ហើយនាំឱ្យគាត់ទទួលរង្វាន់ណូបែលឆ្នាំ១៩០៥។",
    "category": "event",
    "year": "1882",
    "isSymbolic": false
  },
  {
    "date": "24",
    "title": "រដ្ឋប្រហារយោធាអាហ្សង់ទីនចាប់ផ្តើមសង្គ្រាមកខ្វក់",
    "description": "នៅថ្ងៃទី២៤ ខែមីនា ឆ្នាំ១៩៧៦ យោធាអាហ្សង់ទីនបានធ្វើរដ្ឋប្រហារដណ្តើមអំណាច។ ក្នុង 'សង្គ្រាមកខ្វក់' មនុស្សប្រមាណ៣០០០០នាក់ត្រូវបានចាប់ជំរឿន ធ្វើទារុណកម្ម និងសម្លាប់។ ម្តាយផ្លាសាដេម៉ាយូក្លាយជានិមិត្តរូបនៃការតស៊ូ។",
    "category": "event",
    "year": "1976",
    "isSymbolic": false
  },
  {
    "date": "25",
    "title": "ធម៌៖ ការរំលឹកដើមពោធិ៍",
    "description": "ក្រោមដើមពោធិ៍នៅពុទ្ធគយា សិទ្ធត្ថ សាសនគោតម បានត្រាស់ដឹងខ្ពស់បំផុត ហើយក្លាយជាព្រះពុទ្ធ។ ដើមពោធិ៍នៅតែជានិមិត្តរូបនៃការភ្ញាក់រលឹកសម្រាប់មនុស្សរាប់លាននាក់។",
    "category": "event",
    "year": null,
    "isSymbolic": true
  },
  {
    "date": "25",
    "title": "ការលុបបំបាត់ពាណិជ្ជកម្មទាសករនៅចក្រភពអង់គ្លេស",
    "description": "នៅថ្ងៃទី២៥ ខែមីនា ឆ្នាំ១៨០៧ សភាអង់គ្លេសបានអនុម័តច្បាប់លុបបំបាត់ពាណិជ្ជកម្មទាសករ។ ទោះបីការរំដោះពេញលេញមកដល់ឆ្នាំ១៨៣៣ក្តី នេះជាពេលវេលាសំខាន់នៃការតស៊ូប្រឆាំងទាសករពិភពលោក។",
    "category": "event",
    "year": "1807",
    "isSymbolic": false
  },
  {
    "date": "25",
    "title": "ភ្លើងរោងចក្រ Triangle Shirtwaist",
    "description": "នៅថ្ងៃទី២៥ ខែមីនា ឆ្នាំ១៩១១ ភ្លើងបានឆាបឆេះរោងចក្រ Triangle Shirtwaist នៅទីក្រុងញូយ៉ក សម្លាប់កម្មករកាត់ដេរ១៤៦នាក់ — ភាគច្រើនជាស្ត្រីវ័យក្មេងអន្តោប្រវេសន៍។ នេះបានជំរុញកំណែទម្រង់ការងារ។",
    "category": "event",
    "year": "1911",
    "isSymbolic": false
  },
  {
    "date": "26",
    "title": "ថ្ងៃរំដោះបង់ក្លាដេស",
    "description": "ការរំលឹកសេចក្តីប្រកាសឯករាជ្យបង់ក្លាដេសក្នុងឆ្នាំ១៩៧១។ ការរំលឹកអំពីបំណងប្រាថ្នាសកលរបស់មនុស្សសម្រាប់សេរីភាព សេចក្តីថ្លៃថ្នូរ និងការកំណត់ខ្លួនឯង។",
    "category": "event",
    "year": "1971",
    "isSymbolic": false
  },
  {
    "date": "26",
    "title": "សាល់កប្រកាសវ៉ាក់សាំងប៉ូលីយ៉ូជោគជ័យ",
    "description": "នៅថ្ងៃទី២៦ ខែមីនា ឆ្នាំ១៩៥៣ ជូណាស សាល់ក បានប្រកាសថាគាត់បានសាកល្បងវ៉ាក់សាំងប៉ូលីយ៉ូដោយជោគជ័យ។ គាត់មិនបានយកប៉ាតង់ទេ ហើយសួរថា 'តើអ្នកអាចយកប៉ាតង់ព្រះអាទិត្យទេ?' — ធ្វើឱ្យវាឥតគិតថ្លៃសម្រាប់ពិភពលោក។",
    "category": "event",
    "year": "1953",
    "isSymbolic": false
  },
  {
    "date": "26",
    "title": "សន្ធិសញ្ញាសន្តិភាពអេហ្ស៊ីប-អ៊ីស្រាអែលចុះហត្ថលេខា",
    "description": "នៅថ្ងៃទី២៦ ខែមីនា ឆ្នាំ១៩៧៩ អាន់វ៉ា សាដាត និងម៉េណាហេម បេហ្គីន បានចុះហត្ថលេខាលើសន្ធិសញ្ញាសន្តិភាពអេហ្ស៊ីប-អ៊ីស្រាអែលនៅផ្ទះស។ នេះជាកិច្ចព្រមព្រៀងសន្តិភាពដំបូងរវាងអ៊ីស្រាអែលនិងប្រទេសអារ៉ាប់។",
    "category": "event",
    "year": "1979",
    "isSymbolic": false
  },
  {
    "date": "27",
    "title": "ថ្ងៃល្ខោនពិភពលោក",
    "description": "អបអរសិល្បៈល្ខោន។ ណាឌ្យសាស្ត្ររបស់ភារតមុនី និងប្រពៃណីល្ខោនប្រជាប្រិយជាយាននៃការរិះគន់សង្គម និងការបញ្ចេញវប្បធម៌នៅឥណ្ឌាយូរមកហើយ។",
    "category": "event",
    "year": null,
    "isSymbolic": false
  },
  {
    "date": "27",
    "title": "វីលហែលម៍ រ៉នហ្គិនកើត — អ្នករកឃើញកាំរស្មីអ៊ិច",
    "description": "នៅថ្ងៃទី២៧ ខែមីនា ឆ្នាំ១៨៤៥ វីលហែលម៍ រ៉នហ្គិន បានកើត។ ក្នុងឆ្នាំ១៨៩៥ គាត់បានរកឃើញកាំរស្មីអ៊ិច ហើយបដិវត្តន៍វិជ្ជាសាស្ត្រ។ ទទួលរង្វាន់ណូបែលរូបវិទ្យាដំបូងឆ្នាំ១៩០១ ហើយមិនយកប៉ាតង់ទេ។",
    "category": "event",
    "year": "1845",
    "isSymbolic": false
  },
  {
    "date": "27",
    "title": "សភាអាមេរិកអនុញ្ញាតបង្កើតកងទ័ពជើងទឹក",
    "description": "នៅថ្ងៃទី២៧ ខែមីនា ឆ្នាំ១៧៩៤ ប្រធានាធិបតី ចច វ៉ាស៊ីនតោន បានចុះហត្ថលេខាលើច្បាប់កងទ័ពជើងទឹក បង្កើតគ្រឹះកងទ័ពជើងទឹកសហរដ្ឋអាមេរិក។",
    "category": "event",
    "year": "1794",
    "isSymbolic": false
  },
  {
    "date": "28",
    "title": "ធម៌៖ អភិធម្មបិដក",
    "description": "អភិធម្មបិដកជាការវិភាគទស្សនវិជ្ជា និងចិត្តវិទ្យានៃការបង្រៀនព្រះពុទ្ធ។ វាគូសផែនទីចិត្តដោយសេចក្តីលម្អិតដ៏អស្ចារ្យ — ចិត្តវិទ្យាប្រព័ន្ធដំបូងបំផុត។",
    "category": "event",
    "year": null,
    "isSymbolic": true
  },
  {
    "date": "28",
    "title": "គ្រោះថ្នាក់នុយក្លេអ៊ែរកោះបីម៉ាយល៍",
    "description": "នៅថ្ងៃទី២៨ ខែមីនា ឆ្នាំ១៩៧៩ ការរលាយផ្នែកខ្លះបានកើតឡើងនៅរោងចក្រថាមពលនុយក្លេអ៊ែរកោះបីម៉ាយល៍ក្នុងផេនស៊ីលវ៉ានៀ — គ្រោះថ្នាក់នុយក្លេអ៊ែរធ្ងន់បំផុតក្នុងប្រវត្តិសាស្ត្រអាមេរិក។ នេះបានធ្វើកំណែទម្រង់បទប្បញ្ញត្តិសុវត្ថិភាពនុយក្លេអ៊ែរ។",
    "category": "event",
    "year": "1979",
    "isSymbolic": false
  },
  {
    "date": "28",
    "title": "ការធ្លាក់ម៉ាឌ្រីដបញ្ចប់សង្គ្រាមស៊ីវិលអេស្ប៉ាញ",
    "description": "នៅថ្ងៃទី២៨ ខែមីនា ឆ្នាំ១៩៣៩ កងទ័ពជាតិនិយមរបស់ហ្វ្រង់កូបានដណ្តើមម៉ាឌ្រីដ បញ្ចប់សង្គ្រាមស៊ីវិលអេស្ប៉ាញ។ របបផ្តាច់ការរបស់ហ្វ្រង់កូបានបន្តរហូតដល់ឆ្នាំ១៩៧៥។",
    "category": "event",
    "year": "1939",
    "isSymbolic": false
  },
  {
    "date": "29",
    "title": "ធម៌៖ រឿងជាតក",
    "description": "រឿងជាតករៀបរាប់អំពីអតីតជាតិរបស់ព្រះពុទ្ធជាពោធិសត្វ — បង្ហាញពីរបៀបដែលទ្រង់បានបំពេញគុណធម៌ដូចជាការចែករំលែក ភាពអត់ធ្មត់ និងបញ្ញាតាមរយៈជីវិតរាប់អន្លើ។",
    "category": "event",
    "year": null,
    "isSymbolic": true
  },
  {
    "date": "29",
    "title": "ការបះបោររបស់ម៉ង់ហ្គាល់ ប៉ាន់ដេប្រឆាំងអង់គ្លេស",
    "description": "នៅថ្ងៃទី២៩ ខែមីនា ឆ្នាំ១៨៥៧ ទាហាន ម៉ង់ហ្គាល់ ប៉ាន់ដេ បានវាយប្រហារមន្ត្រីអង់គ្លេសនៅបារ៉ាក់ពៅជិតកាល់កាតា។ ការតស៊ូរបស់គាត់ត្រូវបានចាត់ទុកជាផ្កាភ្លើងនៃការបះបោរឥណ្ឌាឆ្នាំ១៨៥៧។",
    "category": "event",
    "year": "1857",
    "isSymbolic": false
  },
  {
    "date": "29",
    "title": "កងទ័ពប្រយុទ្ធអាមេរិកចុងក្រោយចាកចេញពីវៀតណាម",
    "description": "នៅថ្ងៃទី២៩ ខែមីនា ឆ្នាំ១៩៧៣ កងទ័ពប្រយុទ្ធអាមេរិកចុងក្រោយបានចាកចេញពីវៀតណាមខាងត្បូង បញ្ចប់ការចូលរួមយោធាអាមេរិកដោយផ្ទាល់ក្នុងសង្គ្រាមវៀតណាម។ សង្គ្រាមបានបាត់បង់ជីវិតទាហានអាមេរិកជាង៥៨០០០នាក់ និងជនជាតិវៀតណាមប្រមាណ២–៣លាននាក់។",
    "category": "event",
    "year": "1973",
    "isSymbolic": false
  },
  {
    "date": "30",
    "title": "ថ្ងៃរាជស្ថាន",
    "description": "អបអរការបង្កើតរដ្ឋរាជស្ថានក្នុងឆ្នាំ១៩៤៩តាមរយៈការបញ្ចូលគ្នានៃរដ្ឋម្ចាស់ក្សត្រ។ សក្ខីភាពនៃឯកភាពក្នុងភាពចម្រុះរបស់ឥណ្ឌា។",
    "category": "event",
    "year": "1949",
    "isSymbolic": false
  },
  {
    "date": "30",
    "title": "ការប្រើថ្នាំសណ្តំអេធឺដំបូងក្នុងការវះកាត់",
    "description": "នៅថ្ងៃទី៣០ ខែមីនា ឆ្នាំ១៨៤២ វេជ្ជបណ្ឌិត គ្រហ្វដ លង់ បានប្រើថ្នាំសណ្តំអេធឺដំបូងក្នុងការវះកាត់នៅចជឺជីយ៉ា យកដុំសាច់ចេញពីកដោយគ្មានការឈឺចាប់។ នេះត្រូវបានចាត់ទុកជាវឌ្ឍនភាពមនុស្សធម៌ដ៏អស្ចារ្យក្នុងប្រវត្តិសាស្ត្រវេជ្ជសាស្ត្រ។",
    "category": "event",
    "year": "1842",
    "isSymbolic": false
  },
  {
    "date": "30",
    "title": "អាមេរិកទិញអាឡាស្កាពីរុស្ស៊ី",
    "description": "នៅថ្ងៃទី៣០ ខែមីនា ឆ្នាំ១៨៦៧ វីល្លៀម ស្យូអាត បានចុះហត្ថលេខាលើសន្ធិសញ្ញាទិញអាឡាស្កាពីរុស្ស៊ីក្នុងតម្លៃ៧.២លានដុល្លារ។ ទោះបីដើមឡើយត្រូវបានចំអកថា 'ភាពល្ងង់ខ្លៅរបស់ស្យូអាត' ក្តី អាឡាស្កាបានក្លាយជាតម្លៃខ្លាំងនៅពេលក្រោយ។",
    "category": "event",
    "year": "1867",
    "isSymbolic": false
  },
  {
    "date": "31",
    "title": "ធម៌៖ សម្មា សមាធិ",
    "description": "សម្មា សមាធិជាអង្គទីប្រាំបីនៃមគ្គអដ្ឋង្គិក។ តាមរយៈឈាន (ការស្រូបចូលសមាធិ) ចិត្តទទួលបានភាពស្ងប់និងភាពច្បាស់លាស់ដ៏ជ្រៅ។",
    "category": "event",
    "year": null,
    "isSymbolic": true
  },
  {
    "date": "31",
    "title": "ប៉មអេហ្វែលនៅប៉ារីសត្រូវបានបើក",
    "description": "នៅថ្ងៃទី៣១ ខែមីនា ឆ្នាំ១៨៨៩ ហ្គុយស្តាវ អេហ្វែល បានឡើងជណ្តើរ១៦៦៥កាំ ហើយដំកល់ទង់បារាំងនៅកំពូល ដើម្បីបើកប៉មអេហ្វែល។ ប៉មដែកកម្ពស់៣០០ម៉ែត្រជាសំណង់មនុស្សខ្ពស់បំផុតលើពិភពលោកនៅពេលនោះ។",
    "category": "event",
    "year": "1889",
    "isSymbolic": false
  },
  {
    "date": "31",
    "title": "ដាឡៃឡាម៉ារត់គេចពីទីបេមកឥណ្ឌា",
    "description": "នៅថ្ងៃទី៣១ ខែមីនា ឆ្នាំ១៩៥៩ ដាឡៃឡាម៉ាទី១៤ តេនហ្សិន ហ្គ្យាត្សូ បានរត់គេចពីការគាបសង្កត់យោធាចិនលើការបះបោរទីបេ ហើយឆ្លងព្រំដែនឥណ្ឌា។ ជាវ៉ាហារលាល់ នេរុ បានផ្តល់ទីជម្រក ហើយរដ្ឋាភិបាលនិរទេសត្រូវបានបង្កើតនៅធម៌សាឡា។",
    "category": "event",
    "year": "1959",
    "isSymbolic": false
  }
]
